llama_index/tools/box/__init__.py
llama_index/tools/box/ai_extract/__init__.py
llama_index/tools/box/ai_extract/base.py
llama_index/tools/box/ai_prompt/__init__.py
llama_index/tools/box/ai_prompt/base.py
llama_index/tools/box/search/__init__.py
llama_index/tools/box/search/base.py
llama_index/tools/box/search_by_metadata/__init__.py
llama_index/tools/box/search_by_metadata/base.py
llama_index/tools/box/text_extract/__init__.py
llama_index/tools/box/text_extract/base.py
llama_index_tools_box-0.4.1.dist-info/METADATA
llama_index_tools_box-0.4.1.dist-info/WHEEL
llama_index_tools_box-0.4.1.dist-info/licenses/LICENSE
llama_index_tools_box-0.4.1.dist-info/RECORD
