Metadata-Version: 2.4
Name: llama-index-tools-box
Version: 0.4.1
Summary: llama-index tools box integration
Author-email: Rui Barbosa <rbarbosa@box.com>
License-Expression: MIT
License-File: LICENSE
Requires-Python: <4.0,>=3.9
Requires-Dist: box-sdk-gen>=1.5.0
Requires-Dist: llama-index-core<0.15,>=0.13.0
Requires-Dist: llama-index-readers-box<0.5,>=0.4.0
